liblaf/grapes/__init__.py
liblaf/grapes/__init__.pyi
liblaf/grapes/_version.py
liblaf/grapes/_version.pyi
liblaf/grapes/py.typed
liblaf/grapes/_config/__init__.py
liblaf/grapes/_config/__init__.pyi
liblaf/grapes/_config/_config.py
liblaf/grapes/_config/_joblib.py
liblaf/grapes/_config/_logging.py
liblaf/grapes/_config/_pretty.py
liblaf/grapes/_config/_traceback.py
liblaf/grapes/_config/_warnings.py
liblaf/grapes/attrs/__init__.py
liblaf/grapes/attrs/__init__.pyi
liblaf/grapes/attrs/_define.py
liblaf/grapes/bench/__init__.py
liblaf/grapes/bench/__init__.pyi
liblaf/grapes/bench/_bencher.py
liblaf/grapes/bench/_results.py
liblaf/grapes/compat/__init__.py
liblaf/grapes/compat/__init__.pyi
liblaf/grapes/compat/_operator.py
liblaf/grapes/conf/__init__.py
liblaf/grapes/conf/__init__.pyi
liblaf/grapes/conf/_config.py
liblaf/grapes/conf/_constants.py
liblaf/grapes/conf/_entry.py
liblaf/grapes/conf/_field.py
liblaf/grapes/conf/_field_method.py
liblaf/grapes/conf/_field_specifiers.py
liblaf/grapes/conf/_group.py
liblaf/grapes/deps/__init__.py
liblaf/grapes/deps/__init__.pyi
liblaf/grapes/deps/_optional.py
liblaf/grapes/errors/__init__.py
liblaf/grapes/errors/__init__.pyi
liblaf/grapes/errors/_dispatch.py
liblaf/grapes/errors/_match.py
liblaf/grapes/errors/_misc.py
liblaf/grapes/fieldz/__init__.py
liblaf/grapes/fieldz/__init__.pyi
liblaf/grapes/fieldz/_has_fields.py
liblaf/grapes/functools/__init__.py
liblaf/grapes/functools/__init__.pyi
liblaf/grapes/functools/_memorize.py
liblaf/grapes/functools/_wraps.py
liblaf/grapes/functools/_wrapt.py
liblaf/grapes/icecream/__init__.py
liblaf/grapes/icecream/__init__.pyi
liblaf/grapes/icecream/_icecream.py
liblaf/grapes/icecream/_icecream.pyi
liblaf/grapes/icecream/_install.py
liblaf/grapes/icecream/_source.py
liblaf/grapes/itertools/__init__.py
liblaf/grapes/itertools/__init__.pyi
liblaf/grapes/itertools/_as_iterable.py
liblaf/grapes/itertools/_as_sequence.py
liblaf/grapes/itertools/_first_not_none.py
liblaf_grapes-9.1.0.dist-info/METADATA
liblaf_grapes-9.1.0.dist-info/WHEEL
liblaf_grapes-9.1.0.dist-info/licenses/LICENSE
liblaf_grapes-9.1.0.dist-info/RECORD
