Metadata-Version: 2.4
Name: liblaf-grapes
Version: 9.1.0
Summary: 🍇 Supercharge your Python with rich logging, precise timing, and seamless serialization.
Project-URL: Changelog, https://github.com/liblaf/grapes/blob/main/CHANGELOG.md
Project-URL: Documentation, https://liblaf-grapes.readthedocs.io/
Project-URL: Homepage, https://github.com/liblaf/grapes
Project-URL: Issue Tracker, https://github.com/liblaf/grapes/issues
Project-URL: Release Notes, https://github.com/liblaf/grapes/releases
Project-URL: Source Code, https://github.com/liblaf/grapes
Author-email: liblaf <30631553+liblaf@users.noreply.github.com>
License-Expression: MIT
License-File: LICENSE
Classifier: Development Status :: 4 - Beta
Classifier: Intended Audience :: Developers
Classifier: Intended Audience :: Science/Research
Classifier: License :: OSI Approved
Classifier: License :: OSI Approved :: MIT License
Classifier: Operating System :: OS Independent
Classifier: Programming Language :: Python
Classifier: Programming Language :: Python :: 3
Classifier: Programming Language :: Python :: 3.12
Classifier: Programming Language :: Python :: 3.13
Classifier: Programming Language :: Python :: 3.14
Classifier: Topic :: File Formats
Classifier: Topic :: File Formats :: JSON
Classifier: Topic :: Software Development
Classifier: Topic :: Software Development :: Bug Tracking
Classifier: Topic :: Software Development :: Debuggers
Classifier: Topic :: Software Development :: Libraries
Classifier: Topic :: Software Development :: Libraries :: Python Modules
Classifier: Topic :: System
Classifier: Topic :: System :: Logging
Classifier: Topic :: Text Processing
Classifier: Topic :: Text Processing :: Filters
Classifier: Topic :: Utilities
Classifier: Typing :: Typed
Requires-Python: >=3.12
Requires-Dist: about-time<5,>=4
Requires-Dist: asttokens<4,>=3
Requires-Dist: attrs<26,>=25
Requires-Dist: autoregistry<2,>=1
Requires-Dist: cachetools<7,>=6
Requires-Dist: cytoolz<2,>=1
Requires-Dist: environs<15,>=14
Requires-Dist: executing<3,>=2
Requires-Dist: fieldz<0.2,>=0.1
Requires-Dist: joblib<2,>=1
Requires-Dist: lazy-loader<0.5,>=0.4
Requires-Dist: limits<6,>=5
Requires-Dist: msgspec[toml,yaml]<0.21,>=0.20
Requires-Dist: packaging<27,>=26
Requires-Dist: pendulum<4,>=3
Requires-Dist: platformdirs<5,>=4
Requires-Dist: pydantic<3,>=2
Requires-Dist: quantiphy<3,>=2
Requires-Dist: rich<15,>=14
Requires-Dist: toolz<2,>=1
Requires-Dist: typing-extensions<5,>=4
Requires-Dist: wadler-lindig<0.2,>=0.1
Requires-Dist: wrapt<3,>=2
Provides-Extra: bench
Requires-Dist: matplotlib<4,>=3; extra == 'bench'
